{
  "dot pi": ".py",
  "dot py": ".py",
  "dot js": ".js",
  "dot ts": ".ts",
  "dot t s x": ".tsx",
  "dot j s x": ".jsx",
  "dot md": ".md",
  "dot json": ".json",
  "dot yaml": ".yaml",
  "dot toml": ".toml",
  "dot html": ".html",
  "dot css": ".css",
  "dot sh": ".sh",
  "dot bat": ".bat",
  "java script": "JavaScript",
  "type script": "TypeScript",
  "node js": "Node.js",
  "git hub": "GitHub",
  "vs code": "VS Code",
  "json": "JSON",
  "yaml": "YAML",
  "html": "HTML",
  "css": "CSS",
  "url": "URL",
  "api": "API",
  "sdk": "SDK",
  "cli": "CLI",
  "ssh": "SSH",
  "i os": "iOS",
  "mac os": "macOS",
  "pyhton": "Python"
}
